dwc.py
wcld.py
dwc-0.0.3.dist-info/DESCRIPTION.rst
dwc-0.0.3.dist-info/METADATA
dwc-0.0.3.dist-info/RECORD
dwc-0.0.3.dist-info/WHEEL
dwc-0.0.3.dist-info/entry_points.txt
dwc-0.0.3.dist-info/metadata.json
dwc-0.0.3.dist-info/top_level.txt
