Metadata-Version: 2.0
Name: dwc
Version: 0.0.3
Summary: wc clone in Python, plus support directory as arguments
Home-page: https://github.com/hvnsweeting/dwc
Author: Viet Hung Nguyen
Author-email: hvn@familug.org
License: UNKNOWN
Platform: UNKNOWN
